instagibbs/__init__.py
instagibbs/__main__.py
instagibbs/__version__.py
instagibbs/_version.py
instagibbs/methods.py
instagibbs/models.py
instagibbs/preprocess.py
instagibbs/quantities.py
instagibbs/utils.py
instagibbs/config/__init__.py
instagibbs/config/config.py
instagibbs/config/default.yaml
instagibbs/plot/__init__.py
instagibbs/plot/alt.py
instagibbs/plot/helpers.py
instagibbs/plot/mpl.py
instagibbs/plot/structure.py
instagibbs/web/about.md
instagibbs/web/app.py
instagibbs/web/constants.py
instagibbs/web/methods.py
instagibbs/web/models.py
instagibbs/web/style.css
instagibbs-1.0.0.dist-info/METADATA
instagibbs-1.0.0.dist-info/WHEEL
instagibbs-1.0.0.dist-info/entry_points.txt
instagibbs-1.0.0.dist-info/licenses/LICENSE
instagibbs-1.0.0.dist-info/RECORD
