Metadata-Version: 2.4
Name: instagibbs
Version: 1.0.0
Summary: Instant Gibbs free energy estimation coupled to HDX-MS database.
Project-URL: Source, https://github.com/Jhsmit/instagibbs
Author-email: Jochem Smit <jhsmit@gmail.com>
License-Expression: MIT
License-File: LICENSE
Classifier: Programming Language :: Python :: 3.11
Classifier: Programming Language :: Python :: 3.12
Classifier: Programming Language :: Python :: 3.13
Classifier: Programming Language :: Python :: 3.14
Requires-Python: >=3.11
Requires-Dist: altair
Requires-Dist: colorcet
Requires-Dist: dacite
Requires-Dist: hdxms-datasets>=0.3.3
Requires-Dist: hdxrate
Requires-Dist: ipymolstar>=0.0.2
Requires-Dist: numpy
Requires-Dist: polars
Requires-Dist: pyarrow
Requires-Dist: scikit-learn
Requires-Dist: scipy
Requires-Dist: solara
Requires-Dist: tol-colors
Requires-Dist: ultraplot
Requires-Dist: uncertainties
Provides-Extra: dev
Requires-Dist: ipython; extra == 'dev'
